{
  "letter": "L",
  "checkpointRadius": 0.06,
  "comment": "Ă–sterreichische Druckschrift: 2 strokes. 1: vertical topâ†’bottom. 2: baseline foot rightâ†’LEFT (arrow points left).",
  "strokes": [
    {
      "id": 1,
      "comment": "Vertical stroke: top to bottom",
      "checkpoints": [
        {"x": 0.55, "y": 0.22},
        {"x": 0.55, "y": 0.38},
        {"x": 0.55, "y": 0.55},
        {"x": 0.55, "y": 0.72}
      ]
    },
    {
      "id": 2,
      "comment": "Baseline foot: right to LEFT (arrow points left)",
      "checkpoints": [
        {"x": 0.55, "y": 0.72},
        {"x": 0.45, "y": 0.72},
        {"x": 0.35, "y": 0.72}
      ]
    }
  ]
}
