{
  "letter": "Ä",
  "checkpointRadius": 0.05,
  "strokes": [
    {
      "id": 1,
      "checkpoints": [
        {
          "x": 0.429,
          "y": 0.0519
        },
        {
          "x": 0.429,
          "y": 0.0519
        },
        {
          "x": 0.4261,
          "y": 0.0536
        },
        {
          "x": 0.4261,
          "y": 0.0536
        },
        {
          "x": 0.4261,
          "y": 0.0536
        },
        {
          "x": 0.4261,
          "y": 0.0536
        },
        {
          "x": 0.429,
          "y": 0.0519
        },
        {
          "x": 0.429,
          "y": 0.0519
        },
        {
          "x": 0.429,
          "y": 0.0519
        },
        {
          "x": 0.4319,
          "y": 0.0503
        },
        {
          "x": 0.4319,
          "y": 0.0503
        },
        {
          "x": 0.4319,
          "y": 0.0503
        },
        {
          "x": 0.4319,
          "y": 0.0503
        },
        {
          "x": 0.429,
          "y": 0.0519
        },
        {
          "x": 0.429,
          "y": 0.0519
        }
      ],
      "comment": "auto-l"
    },
    {
      "id": 2,
      "checkpoints": [
        {
          "x": 0.7884,
          "y": 0.0471
        },
        {
          "x": 0.7884,
          "y": 0.0471
        },
        {
          "x": 0.7855,
          "y": 0.0487
        },
        {
          "x": 0.7855,
          "y": 0.0487
        },
        {
          "x": 0.7855,
          "y": 0.0487
        },
        {
          "x": 0.7855,
          "y": 0.0487
        },
        {
          "x": 0.7826,
          "y": 0.0503
        },
        {
          "x": 0.7826,
          "y": 0.0503
        },
        {
          "x": 0.7826,
          "y": 0.0503
        },
        {
          "x": 0.7797,
          "y": 0.0519
        },
        {
          "x": 0.7797,
          "y": 0.0519
        },
        {
          "x": 0.7797,
          "y": 0.0519
        },
        {
          "x": 0.7797,
          "y": 0.0519
        },
        {
          "x": 0.7768,
          "y": 0.0536
        },
        {
          "x": 0.7768,
          "y": 0.0536
        }
      ],
      "comment": "auto-d"
    },
    {
      "id": 3,
      "checkpoints": [
        {
          "x": 0.9333,
          "y": 0.9627
        },
        {
          "x": 0.9275,
          "y": 0.9464
        },
        {
          "x": 0.9188,
          "y": 0.9286
        },
        {
          "x": 0.9101,
          "y": 0.9107
        },
        {
          "x": 0.9014,
          "y": 0.8929
        },
        {
          "x": 0.8928,
          "y": 0.875
        },
        {
          "x": 0.887,
          "y": 0.8588
        },
        {
          "x": 0.8783,
          "y": 0.8409
        },
        {
          "x": 0.8696,
          "y": 0.8231
        },
        {
          "x": 0.8609,
          "y": 0.8052
        },
        {
          "x": 0.8522,
          "y": 0.7873
        },
        {
          "x": 0.8435,
          "y": 0.7711
        },
        {
          "x": 0.8348,
          "y": 0.7532
        },
        {
          "x": 0.8261,
          "y": 0.7354
        },
        {
          "x": 0.8203,
          "y": 0.7175
        },
        {
          "x": 0.8116,
          "y": 0.6997
        },
        {
          "x": 0.8029,
          "y": 0.6834
        },
        {
          "x": 0.7942,
          "y": 0.6786
        },
        {
          "x": 0.7826,
          "y": 0.6623
        },
        {
          "x": 0.7768,
          "y": 0.6445
        },
        {
          "x": 0.7739,
          "y": 0.6266
        },
        {
          "x": 0.7681,
          "y": 0.6071
        },
        {
          "x": 0.7594,
          "y": 0.5909
        },
        {
          "x": 0.7507,
          "y": 0.5731
        },
        {
          "x": 0.742,
          "y": 0.5552
        },
        {
          "x": 0.7333,
          "y": 0.5373
        },
        {
          "x": 0.7246,
          "y": 0.5195
        },
        {
          "x": 0.7188,
          "y": 0.5032
        },
        {
          "x": 0.7101,
          "y": 0.4854
        },
        {
          "x": 0.7014,
          "y": 0.4675
        },
        {
          "x": 0.6928,
          "y": 0.4497
        },
        {
          "x": 0.6841,
          "y": 0.4318
        },
        {
          "x": 0.6754,
          "y": 0.414
        },
        {
          "x": 0.6696,
          "y": 0.3977
        },
        {
          "x": 0.6609,
          "y": 0.3799
        },
        {
          "x": 0.6522,
          "y": 0.362
        },
        {
          "x": 0.6435,
          "y": 0.3442
        },
        {
          "x": 0.6348,
          "y": 0.3263
        },
        {
          "x": 0.6261,
          "y": 0.3101
        },
        {
          "x": 0.6116,
          "y": 0.2938
        },
        {
          "x": 0.5855,
          "y": 0.2841
        },
        {
          "x": 0.5739,
          "y": 0.2857
        },
        {
          "x": 0.5652,
          "y": 0.289
        },
        {
          "x": 0.5362,
          "y": 0.2971
        },
        {
          "x": 0.5275,
          "y": 0.3003
        },
        {
          "x": 0.5217,
          "y": 0.3052
        },
        {
          "x": 0.5188,
          "y": 0.3117
        },
        {
          "x": 0.5072,
          "y": 0.3279
        },
        {
          "x": 0.4957,
          "y": 0.3442
        },
        {
          "x": 0.4812,
          "y": 0.362
        },
        {
          "x": 0.4696,
          "y": 0.3782
        },
        {
          "x": 0.458,
          "y": 0.3945
        },
        {
          "x": 0.4464,
          "y": 0.4123
        },
        {
          "x": 0.4348,
          "y": 0.4286
        },
        {
          "x": 0.4232,
          "y": 0.4448
        },
        {
          "x": 0.4116,
          "y": 0.4627
        },
        {
          "x": 0.4,
          "y": 0.4789
        },
        {
          "x": 0.3884,
          "y": 0.4951
        },
        {
          "x": 0.3768,
          "y": 0.513
        },
        {
          "x": 0.3652,
          "y": 0.5292
        },
        {
          "x": 0.3536,
          "y": 0.5455
        },
        {
          "x": 0.342,
          "y": 0.5633
        },
        {
          "x": 0.3304,
          "y": 0.5795
        },
        {
          "x": 0.3188,
          "y": 0.5958
        },
        {
          "x": 0.3072,
          "y": 0.6136
        },
        {
          "x": 0.2986,
          "y": 0.6315
        },
        {
          "x": 0.2957,
          "y": 0.6494
        },
        {
          "x": 0.2899,
          "y": 0.6672
        },
        {
          "x": 0.2725,
          "y": 0.6818
        },
        {
          "x": 0.2522,
          "y": 0.6932
        },
        {
          "x": 0.2406,
          "y": 0.7094
        },
        {
          "x": 0.229,
          "y": 0.7273
        },
        {
          "x": 0.2174,
          "y": 0.7435
        },
        {
          "x": 0.2058,
          "y": 0.7597
        },
        {
          "x": 0.1913,
          "y": 0.7776
        },
        {
          "x": 0.1884,
          "y": 0.7825
        },
        {
          "x": 0.1768,
          "y": 0.7987
        },
        {
          "x": 0.1652,
          "y": 0.8166
        },
        {
          "x": 0.1536,
          "y": 0.8328
        },
        {
          "x": 0.142,
          "y": 0.849
        },
        {
          "x": 0.1304,
          "y": 0.8669
        },
        {
          "x": 0.1188,
          "y": 0.8831
        },
        {
          "x": 0.1072,
          "y": 0.8994
        },
        {
          "x": 0.0957,
          "y": 0.9172
        },
        {
          "x": 0.0841,
          "y": 0.9334
        },
        {
          "x": 0.0725,
          "y": 0.9497
        },
        {
          "x": 0.0609,
          "y": 0.9675
        },
        {
          "x": 0.0638,
          "y": 0.9692
        }
      ],
      "comment": "auto-d"
    },
    {
      "id": 4,
      "checkpoints": [
        {
          "x": 0.7826,
          "y": 0.6753
        },
        {
          "x": 0.7507,
          "y": 0.6786
        },
        {
          "x": 0.7159,
          "y": 0.6786
        },
        {
          "x": 0.6812,
          "y": 0.6786
        },
        {
          "x": 0.6464,
          "y": 0.6786
        },
        {
          "x": 0.6116,
          "y": 0.6786
        },
        {
          "x": 0.5768,
          "y": 0.6786
        },
        {
          "x": 0.542,
          "y": 0.6786
        },
        {
          "x": 0.5072,
          "y": 0.6786
        },
        {
          "x": 0.4725,
          "y": 0.6786
        },
        {
          "x": 0.4377,
          "y": 0.6786
        },
        {
          "x": 0.4029,
          "y": 0.6786
        },
        {
          "x": 0.3681,
          "y": 0.6786
        },
        {
          "x": 0.3333,
          "y": 0.6786
        },
        {
          "x": 0.2986,
          "y": 0.6786
        },
        {
          "x": 0.287,
          "y": 0.6769
        }
      ],
      "comment": "auto-h"
    }
  ],
  "skeleton": [
    {
      "x": 0.7884,
      "y": 0.0471
    },
    {
      "x": 0.7855,
      "y": 0.0487
    },
    {
      "x": 0.7826,
      "y": 0.0503
    },
    {
      "x": 0.7797,
      "y": 0.0519
    },
    {
      "x": 0.4261,
      "y": 0.0536
    },
    {
      "x": 0.5855,
      "y": 0.25
    },
    {
      "x": 0.5855,
      "y": 0.2532
    },
    {
      "x": 0.5855,
      "y": 0.2565
    },
    {
      "x": 0.5855,
      "y": 0.2597
    },
    {
      "x": 0.5855,
      "y": 0.263
    },
    {
      "x": 0.5855,
      "y": 0.2662
    },
    {
      "x": 0.5855,
      "y": 0.2695
    },
    {
      "x": 0.5826,
      "y": 0.2727
    },
    {
      "x": 0.5826,
      "y": 0.276
    },
    {
      "x": 0.5826,
      "y": 0.2792
    },
    {
      "x": 0.5826,
      "y": 0.2825
    },
    {
      "x": 0.5826,
      "y": 0.2841
    },
    {
      "x": 0.5884,
      "y": 0.2841
    },
    {
      "x": 0.5768,
      "y": 0.2857
    },
    {
      "x": 0.5681,
      "y": 0.2873
    },
    {
      "x": 0.5942,
      "y": 0.2873
    },
    {
      "x": 0.5623,
      "y": 0.289
    },
    {
      "x": 0.6,
      "y": 0.289
    },
    {
      "x": 0.6029,
      "y": 0.2906
    },
    {
      "x": 0.5536,
      "y": 0.2922
    },
    {
      "x": 0.6087,
      "y": 0.2922
    },
    {
      "x": 0.5507,
      "y": 0.2938
    },
    {
      "x": 0.6145,
      "y": 0.2938
    },
    {
      "x": 0.5449,
      "y": 0.2955
    },
    {
      "x": 0.5362,
      "y": 0.2971
    },
    {
      "x": 0.6203,
      "y": 0.2971
    },
    {
      "x": 0.6232,
      "y": 0.2987
    },
    {
      "x": 0.5304,
      "y": 0.3003
    },
    {
      "x": 0.5246,
      "y": 0.3019
    },
    {
      "x": 0.5246,
      "y": 0.3036
    },
    {
      "x": 0.5217,
      "y": 0.3052
    },
    {
      "x": 0.5217,
      "y": 0.3068
    },
    {
      "x": 0.5188,
      "y": 0.3084
    },
    {
      "x": 0.5188,
      "y": 0.3101
    },
    {
      "x": 0.5188,
      "y": 0.3117
    },
    {
      "x": 0.5159,
      "y": 0.3133
    },
    {
      "x": 0.5159,
      "y": 0.3149
    },
    {
      "x": 0.513,
      "y": 0.3166
    },
    {
      "x": 0.513,
      "y": 0.3182
    },
    {
      "x": 0.513,
      "y": 0.3198
    },
    {
      "x": 0.5101,
      "y": 0.3214
    },
    {
      "x": 0.5101,
      "y": 0.3231
    },
    {
      "x": 0.5072,
      "y": 0.3247
    },
    {
      "x": 0.5072,
      "y": 0.3263
    },
    {
      "x": 0.5072,
      "y": 0.3279
    },
    {
      "x": 0.5043,
      "y": 0.3295
    },
    {
      "x": 0.5043,
      "y": 0.3312
    },
    {
      "x": 0.5014,
      "y": 0.3328
    },
    {
      "x": 0.5014,
      "y": 0.3344
    },
    {
      "x": 0.5014,
      "y": 0.336
    },
    {
      "x": 0.4986,
      "y": 0.3377
    },
    {
      "x": 0.4986,
      "y": 0.3393
    },
    {
      "x": 0.4957,
      "y": 0.3409
    },
    {
      "x": 0.4957,
      "y": 0.3425
    },
    {
      "x": 0.4957,
      "y": 0.3442
    },
    {
      "x": 0.4928,
      "y": 0.3458
    },
    {
      "x": 0.4928,
      "y": 0.3474
    },
    {
      "x": 0.4928,
      "y": 0.349
    },
    {
      "x": 0.4899,
      "y": 0.3506
    },
    {
      "x": 0.4899,
      "y": 0.3523
    },
    {
      "x": 0.487,
      "y": 0.3539
    },
    {
      "x": 0.487,
      "y": 0.3555
    },
    {
      "x": 0.487,
      "y": 0.3571
    },
    {
      "x": 0.4841,
      "y": 0.3588
    },
    {
      "x": 0.4841,
      "y": 0.3604
    },
    {
      "x": 0.4812,
      "y": 0.362
    },
    {
      "x": 0.4812,
      "y": 0.3636
    },
    {
      "x": 0.4812,
      "y": 0.3653
    },
    {
      "x": 0.4783,
      "y": 0.3669
    },
    {
      "x": 0.4783,
      "y": 0.3685
    },
    {
      "x": 0.4754,
      "y": 0.3701
    },
    {
      "x": 0.4754,
      "y": 0.3718
    },
    {
      "x": 0.4754,
      "y": 0.3734
    },
    {
      "x": 0.4725,
      "y": 0.375
    },
    {
      "x": 0.4725,
      "y": 0.3766
    },
    {
      "x": 0.4696,
      "y": 0.3782
    },
    {
      "x": 0.4696,
      "y": 0.3799
    },
    {
      "x": 0.4696,
      "y": 0.3815
    },
    {
      "x": 0.4667,
      "y": 0.3831
    },
    {
      "x": 0.4667,
      "y": 0.3847
    },
    {
      "x": 0.4638,
      "y": 0.3864
    },
    {
      "x": 0.4638,
      "y": 0.388
    },
    {
      "x": 0.4638,
      "y": 0.3896
    },
    {
      "x": 0.4609,
      "y": 0.3912
    },
    {
      "x": 0.4609,
      "y": 0.3929
    },
    {
      "x": 0.458,
      "y": 0.3945
    },
    {
      "x": 0.458,
      "y": 0.3961
    },
    {
      "x": 0.458,
      "y": 0.3977
    },
    {
      "x": 0.4551,
      "y": 0.3994
    },
    {
      "x": 0.4551,
      "y": 0.401
    },
    {
      "x": 0.4522,
      "y": 0.4026
    },
    {
      "x": 0.4522,
      "y": 0.4042
    },
    {
      "x": 0.4522,
      "y": 0.4058
    },
    {
      "x": 0.4493,
      "y": 0.4075
    },
    {
      "x": 0.4493,
      "y": 0.4091
    },
    {
      "x": 0.4464,
      "y": 0.4107
    },
    {
      "x": 0.4464,
      "y": 0.4123
    },
    {
      "x": 0.4464,
      "y": 0.414
    },
    {
      "x": 0.4435,
      "y": 0.4156
    },
    {
      "x": 0.4435,
      "y": 0.4172
    },
    {
      "x": 0.4435,
      "y": 0.4188
    },
    {
      "x": 0.4406,
      "y": 0.4205
    },
    {
      "x": 0.4406,
      "y": 0.4221
    },
    {
      "x": 0.4377,
      "y": 0.4237
    },
    {
      "x": 0.4377,
      "y": 0.4253
    },
    {
      "x": 0.4377,
      "y": 0.4269
    },
    {
      "x": 0.4348,
      "y": 0.4286
    },
    {
      "x": 0.4348,
      "y": 0.4302
    },
    {
      "x": 0.4319,
      "y": 0.4318
    },
    {
      "x": 0.4319,
      "y": 0.4334
    },
    {
      "x": 0.4319,
      "y": 0.4351
    },
    {
      "x": 0.429,
      "y": 0.4367
    },
    {
      "x": 0.429,
      "y": 0.4383
    },
    {
      "x": 0.4261,
      "y": 0.4399
    },
    {
      "x": 0.4261,
      "y": 0.4416
    },
    {
      "x": 0.4261,
      "y": 0.4432
    },
    {
      "x": 0.4232,
      "y": 0.4448
    },
    {
      "x": 0.4232,
      "y": 0.4464
    },
    {
      "x": 0.4203,
      "y": 0.4481
    },
    {
      "x": 0.4203,
      "y": 0.4497
    },
    {
      "x": 0.4203,
      "y": 0.4513
    },
    {
      "x": 0.4174,
      "y": 0.4529
    },
    {
      "x": 0.4174,
      "y": 0.4545
    },
    {
      "x": 0.4145,
      "y": 0.4562
    },
    {
      "x": 0.4145,
      "y": 0.4578
    },
    {
      "x": 0.4145,
      "y": 0.4594
    },
    {
      "x": 0.4116,
      "y": 0.461
    },
    {
      "x": 0.4116,
      "y": 0.4627
    },
    {
      "x": 0.4116,
      "y": 0.4643
    },
    {
      "x": 0.4087,
      "y": 0.4659
    },
    {
      "x": 0.4087,
      "y": 0.4675
    },
    {
      "x": 0.4058,
      "y": 0.4692
    },
    {
      "x": 0.4058,
      "y": 0.4708
    },
    {
      "x": 0.4058,
      "y": 0.4724
    },
    {
      "x": 0.4029,
      "y": 0.474
    },
    {
      "x": 0.4029,
      "y": 0.4756
    },
    {
      "x": 0.4,
      "y": 0.4773
    },
    {
      "x": 0.4,
      "y": 0.4789
    },
    {
      "x": 0.4,
      "y": 0.4805
    },
    {
      "x": 0.3971,
      "y": 0.4821
    },
    {
      "x": 0.3971,
      "y": 0.4838
    },
    {
      "x": 0.3971,
      "y": 0.4854
    },
    {
      "x": 0.3942,
      "y": 0.487
    },
    {
      "x": 0.3942,
      "y": 0.4886
    },
    {
      "x": 0.3913,
      "y": 0.4903
    },
    {
      "x": 0.3913,
      "y": 0.4919
    },
    {
      "x": 0.3913,
      "y": 0.4935
    },
    {
      "x": 0.3884,
      "y": 0.4951
    },
    {
      "x": 0.3884,
      "y": 0.4968
    },
    {
      "x": 0.3855,
      "y": 0.4984
    },
    {
      "x": 0.3855,
      "y": 0.5
    },
    {
      "x": 0.3855,
      "y": 0.5016
    },
    {
      "x": 0.3826,
      "y": 0.5032
    },
    {
      "x": 0.3826,
      "y": 0.5049
    },
    {
      "x": 0.3826,
      "y": 0.5065
    },
    {
      "x": 0.3797,
      "y": 0.5081
    },
    {
      "x": 0.3797,
      "y": 0.5097
    },
    {
      "x": 0.3768,
      "y": 0.5114
    },
    {
      "x": 0.3768,
      "y": 0.513
    },
    {
      "x": 0.3768,
      "y": 0.5146
    },
    {
      "x": 0.3739,
      "y": 0.5162
    },
    {
      "x": 0.3739,
      "y": 0.5179
    },
    {
      "x": 0.371,
      "y": 0.5195
    },
    {
      "x": 0.371,
      "y": 0.5211
    },
    {
      "x": 0.371,
      "y": 0.5227
    },
    {
      "x": 0.3681,
      "y": 0.5244
    },
    {
      "x": 0.3681,
      "y": 0.526
    },
    {
      "x": 0.3681,
      "y": 0.5276
    },
    {
      "x": 0.3652,
      "y": 0.5292
    },
    {
      "x": 0.3652,
      "y": 0.5308
    },
    {
      "x": 0.3623,
      "y": 0.5325
    },
    {
      "x": 0.3623,
      "y": 0.5341
    },
    {
      "x": 0.3623,
      "y": 0.5357
    },
    {
      "x": 0.3594,
      "y": 0.5373
    },
    {
      "x": 0.3594,
      "y": 0.539
    },
    {
      "x": 0.3565,
      "y": 0.5406
    },
    {
      "x": 0.3565,
      "y": 0.5422
    },
    {
      "x": 0.3565,
      "y": 0.5438
    },
    {
      "x": 0.3536,
      "y": 0.5455
    },
    {
      "x": 0.3536,
      "y": 0.5471
    },
    {
      "x": 0.3536,
      "y": 0.5487
    },
    {
      "x": 0.3507,
      "y": 0.5503
    },
    {
      "x": 0.3507,
      "y": 0.5519
    },
    {
      "x": 0.3478,
      "y": 0.5536
    },
    {
      "x": 0.3478,
      "y": 0.5552
    },
    {
      "x": 0.3478,
      "y": 0.5568
    },
    {
      "x": 0.3449,
      "y": 0.5584
    },
    {
      "x": 0.3449,
      "y": 0.5601
    },
    {
      "x": 0.342,
      "y": 0.5617
    },
    {
      "x": 0.342,
      "y": 0.5633
    },
    {
      "x": 0.342,
      "y": 0.5649
    },
    {
      "x": 0.3391,
      "y": 0.5666
    },
    {
      "x": 0.3391,
      "y": 0.5682
    },
    {
      "x": 0.3391,
      "y": 0.5698
    },
    {
      "x": 0.3362,
      "y": 0.5714
    },
    {
      "x": 0.3362,
      "y": 0.5731
    },
    {
      "x": 0.3333,
      "y": 0.5747
    },
    {
      "x": 0.3333,
      "y": 0.5763
    },
    {
      "x": 0.3333,
      "y": 0.5779
    },
    {
      "x": 0.3304,
      "y": 0.5795
    },
    {
      "x": 0.3304,
      "y": 0.5812
    },
    {
      "x": 0.3275,
      "y": 0.5828
    },
    {
      "x": 0.3275,
      "y": 0.5844
    },
    {
      "x": 0.3275,
      "y": 0.586
    },
    {
      "x": 0.3246,
      "y": 0.5877
    },
    {
      "x": 0.3246,
      "y": 0.5893
    },
    {
      "x": 0.3246,
      "y": 0.5909
    },
    {
      "x": 0.3217,
      "y": 0.5925
    },
    {
      "x": 0.3217,
      "y": 0.5942
    },
    {
      "x": 0.3188,
      "y": 0.5958
    },
    {
      "x": 0.3188,
      "y": 0.5974
    },
    {
      "x": 0.3188,
      "y": 0.599
    },
    {
      "x": 0.3159,
      "y": 0.6006
    },
    {
      "x": 0.3159,
      "y": 0.6023
    },
    {
      "x": 0.313,
      "y": 0.6039
    },
    {
      "x": 0.313,
      "y": 0.6055
    },
    {
      "x": 0.313,
      "y": 0.6071
    },
    {
      "x": 0.3101,
      "y": 0.6088
    },
    {
      "x": 0.3101,
      "y": 0.6104
    },
    {
      "x": 0.3072,
      "y": 0.612
    },
    {
      "x": 0.3072,
      "y": 0.6136
    },
    {
      "x": 0.3072,
      "y": 0.6153
    },
    {
      "x": 0.3043,
      "y": 0.6169
    },
    {
      "x": 0.3043,
      "y": 0.6185
    },
    {
      "x": 0.3043,
      "y": 0.6201
    },
    {
      "x": 0.3014,
      "y": 0.6218
    },
    {
      "x": 0.3014,
      "y": 0.6234
    },
    {
      "x": 0.3014,
      "y": 0.625
    },
    {
      "x": 0.3014,
      "y": 0.6266
    },
    {
      "x": 0.3014,
      "y": 0.6282
    },
    {
      "x": 0.3014,
      "y": 0.6299
    },
    {
      "x": 0.2986,
      "y": 0.6315
    },
    {
      "x": 0.2986,
      "y": 0.6331
    },
    {
      "x": 0.2986,
      "y": 0.6347
    },
    {
      "x": 0.2986,
      "y": 0.6364
    },
    {
      "x": 0.2986,
      "y": 0.638
    },
    {
      "x": 0.2986,
      "y": 0.6396
    },
    {
      "x": 0.2986,
      "y": 0.6412
    },
    {
      "x": 0.2957,
      "y": 0.6429
    },
    {
      "x": 0.2957,
      "y": 0.6445
    },
    {
      "x": 0.2957,
      "y": 0.6461
    },
    {
      "x": 0.2957,
      "y": 0.6477
    },
    {
      "x": 0.2957,
      "y": 0.6494
    },
    {
      "x": 0.2957,
      "y": 0.651
    },
    {
      "x": 0.2928,
      "y": 0.6526
    },
    {
      "x": 0.2928,
      "y": 0.6542
    },
    {
      "x": 0.2928,
      "y": 0.6558
    },
    {
      "x": 0.2928,
      "y": 0.6575
    },
    {
      "x": 0.2928,
      "y": 0.6591
    },
    {
      "x": 0.2928,
      "y": 0.6607
    },
    {
      "x": 0.2899,
      "y": 0.6623
    },
    {
      "x": 0.2899,
      "y": 0.664
    },
    {
      "x": 0.2899,
      "y": 0.6656
    },
    {
      "x": 0.2899,
      "y": 0.6672
    },
    {
      "x": 0.2899,
      "y": 0.6688
    },
    {
      "x": 0.2899,
      "y": 0.6705
    },
    {
      "x": 0.287,
      "y": 0.6721
    },
    {
      "x": 0.287,
      "y": 0.6737
    },
    {
      "x": 0.287,
      "y": 0.6753
    },
    {
      "x": 0.7855,
      "y": 0.6753
    },
    {
      "x": 0.287,
      "y": 0.6769
    },
    {
      "x": 0.7884,
      "y": 0.6769
    },
    {
      "x": 0.2899,
      "y": 0.6786
    },
    {
      "x": 0.2957,
      "y": 0.6786
    },
    {
      "x": 0.3014,
      "y": 0.6786
    },
    {
      "x": 0.3072,
      "y": 0.6786
    },
    {
      "x": 0.313,
      "y": 0.6786
    },
    {
      "x": 0.3188,
      "y": 0.6786
    },
    {
      "x": 0.3246,
      "y": 0.6786
    },
    {
      "x": 0.3304,
      "y": 0.6786
    },
    {
      "x": 0.3362,
      "y": 0.6786
    },
    {
      "x": 0.342,
      "y": 0.6786
    },
    {
      "x": 0.3478,
      "y": 0.6786
    },
    {
      "x": 0.3536,
      "y": 0.6786
    },
    {
      "x": 0.3594,
      "y": 0.6786
    },
    {
      "x": 0.3652,
      "y": 0.6786
    },
    {
      "x": 0.371,
      "y": 0.6786
    },
    {
      "x": 0.3768,
      "y": 0.6786
    },
    {
      "x": 0.3826,
      "y": 0.6786
    },
    {
      "x": 0.3884,
      "y": 0.6786
    },
    {
      "x": 0.3942,
      "y": 0.6786
    },
    {
      "x": 0.4,
      "y": 0.6786
    },
    {
      "x": 0.4058,
      "y": 0.6786
    },
    {
      "x": 0.4116,
      "y": 0.6786
    },
    {
      "x": 0.4174,
      "y": 0.6786
    },
    {
      "x": 0.4232,
      "y": 0.6786
    },
    {
      "x": 0.429,
      "y": 0.6786
    },
    {
      "x": 0.4348,
      "y": 0.6786
    },
    {
      "x": 0.4406,
      "y": 0.6786
    },
    {
      "x": 0.4464,
      "y": 0.6786
    },
    {
      "x": 0.4522,
      "y": 0.6786
    },
    {
      "x": 0.458,
      "y": 0.6786
    },
    {
      "x": 0.4638,
      "y": 0.6786
    },
    {
      "x": 0.4696,
      "y": 0.6786
    },
    {
      "x": 0.4754,
      "y": 0.6786
    },
    {
      "x": 0.4812,
      "y": 0.6786
    },
    {
      "x": 0.487,
      "y": 0.6786
    },
    {
      "x": 0.4928,
      "y": 0.6786
    },
    {
      "x": 0.4986,
      "y": 0.6786
    },
    {
      "x": 0.5043,
      "y": 0.6786
    },
    {
      "x": 0.5101,
      "y": 0.6786
    },
    {
      "x": 0.5159,
      "y": 0.6786
    },
    {
      "x": 0.5217,
      "y": 0.6786
    },
    {
      "x": 0.5275,
      "y": 0.6786
    },
    {
      "x": 0.5333,
      "y": 0.6786
    },
    {
      "x": 0.5391,
      "y": 0.6786
    },
    {
      "x": 0.5449,
      "y": 0.6786
    },
    {
      "x": 0.5507,
      "y": 0.6786
    },
    {
      "x": 0.5565,
      "y": 0.6786
    },
    {
      "x": 0.5623,
      "y": 0.6786
    },
    {
      "x": 0.5681,
      "y": 0.6786
    },
    {
      "x": 0.5739,
      "y": 0.6786
    },
    {
      "x": 0.5797,
      "y": 0.6786
    },
    {
      "x": 0.5855,
      "y": 0.6786
    },
    {
      "x": 0.5913,
      "y": 0.6786
    },
    {
      "x": 0.5971,
      "y": 0.6786
    },
    {
      "x": 0.6029,
      "y": 0.6786
    },
    {
      "x": 0.6087,
      "y": 0.6786
    },
    {
      "x": 0.6145,
      "y": 0.6786
    },
    {
      "x": 0.6203,
      "y": 0.6786
    },
    {
      "x": 0.6261,
      "y": 0.6786
    },
    {
      "x": 0.6319,
      "y": 0.6786
    },
    {
      "x": 0.6377,
      "y": 0.6786
    },
    {
      "x": 0.6435,
      "y": 0.6786
    },
    {
      "x": 0.6493,
      "y": 0.6786
    },
    {
      "x": 0.6551,
      "y": 0.6786
    },
    {
      "x": 0.6609,
      "y": 0.6786
    },
    {
      "x": 0.6667,
      "y": 0.6786
    },
    {
      "x": 0.6725,
      "y": 0.6786
    },
    {
      "x": 0.6783,
      "y": 0.6786
    },
    {
      "x": 0.6841,
      "y": 0.6786
    },
    {
      "x": 0.6899,
      "y": 0.6786
    },
    {
      "x": 0.6957,
      "y": 0.6786
    },
    {
      "x": 0.7014,
      "y": 0.6786
    },
    {
      "x": 0.7072,
      "y": 0.6786
    },
    {
      "x": 0.713,
      "y": 0.6786
    },
    {
      "x": 0.7188,
      "y": 0.6786
    },
    {
      "x": 0.7246,
      "y": 0.6786
    },
    {
      "x": 0.7304,
      "y": 0.6786
    },
    {
      "x": 0.7362,
      "y": 0.6786
    },
    {
      "x": 0.742,
      "y": 0.6786
    },
    {
      "x": 0.7478,
      "y": 0.6786
    },
    {
      "x": 0.7536,
      "y": 0.6786
    },
    {
      "x": 0.7594,
      "y": 0.6786
    },
    {
      "x": 0.7652,
      "y": 0.6786
    },
    {
      "x": 0.771,
      "y": 0.6786
    },
    {
      "x": 0.7768,
      "y": 0.6786
    },
    {
      "x": 0.7942,
      "y": 0.6786
    },
    {
      "x": 0.2783,
      "y": 0.6802
    },
    {
      "x": 0.2696,
      "y": 0.6818
    },
    {
      "x": 0.8,
      "y": 0.6818
    },
    {
      "x": 0.2667,
      "y": 0.6834
    },
    {
      "x": 0.258,
      "y": 0.6851
    },
    {
      "x": 0.8029,
      "y": 0.6851
    },
    {
      "x": 0.8029,
      "y": 0.6867
    },
    {
      "x": 0.8058,
      "y": 0.6883
    },
    {
      "x": 0.8058,
      "y": 0.6899
    },
    {
      "x": 0.8058,
      "y": 0.6916
    },
    {
      "x": 0.8087,
      "y": 0.6932
    },
    {
      "x": 0.8087,
      "y": 0.6948
    },
    {
      "x": 0.8087,
      "y": 0.6964
    },
    {
      "x": 0.8087,
      "y": 0.6981
    },
    {
      "x": 0.8116,
      "y": 0.6997
    },
    {
      "x": 0.8116,
      "y": 0.7013
    },
    {
      "x": 0.8116,
      "y": 0.7029
    },
    {
      "x": 0.8116,
      "y": 0.7045
    },
    {
      "x": 0.8145,
      "y": 0.7062
    },
    {
      "x": 0.8145,
      "y": 0.7078
    },
    {
      "x": 0.8145,
      "y": 0.7094
    },
    {
      "x": 0.8145,
      "y": 0.711
    },
    {
      "x": 0.8174,
      "y": 0.7127
    },
    {
      "x": 0.8174,
      "y": 0.7143
    },
    {
      "x": 0.8174,
      "y": 0.7159
    },
    {
      "x": 0.8203,
      "y": 0.7175
    },
    {
      "x": 0.8203,
      "y": 0.7192
    },
    {
      "x": 0.8203,
      "y": 0.7208
    },
    {
      "x": 0.8203,
      "y": 0.7224
    },
    {
      "x": 0.8232,
      "y": 0.724
    },
    {
      "x": 0.8232,
      "y": 0.7256
    },
    {
      "x": 0.8232,
      "y": 0.7273
    },
    {
      "x": 0.8232,
      "y": 0.7289
    },
    {
      "x": 0.8261,
      "y": 0.7305
    },
    {
      "x": 0.8261,
      "y": 0.7321
    },
    {
      "x": 0.8261,
      "y": 0.7338
    },
    {
      "x": 0.8261,
      "y": 0.7354
    },
    {
      "x": 0.829,
      "y": 0.737
    },
    {
      "x": 0.829,
      "y": 0.7386
    },
    {
      "x": 0.829,
      "y": 0.7403
    },
    {
      "x": 0.8319,
      "y": 0.7419
    },
    {
      "x": 0.8319,
      "y": 0.7435
    },
    {
      "x": 0.8319,
      "y": 0.7451
    },
    {
      "x": 0.8319,
      "y": 0.7468
    },
    {
      "x": 0.8348,
      "y": 0.7484
    },
    {
      "x": 0.8348,
      "y": 0.75
    },
    {
      "x": 0.8348,
      "y": 0.7516
    },
    {
      "x": 0.8348,
      "y": 0.7532
    },
    {
      "x": 0.8377,
      "y": 0.7549
    },
    {
      "x": 0.8377,
      "y": 0.7565
    },
    {
      "x": 0.8377,
      "y": 0.7581
    },
    {
      "x": 0.8377,
      "y": 0.7597
    },
    {
      "x": 0.8406,
      "y": 0.7614
    },
    {
      "x": 0.8406,
      "y": 0.763
    },
    {
      "x": 0.8406,
      "y": 0.7646
    },
    {
      "x": 0.8435,
      "y": 0.7662
    },
    {
      "x": 0.8435,
      "y": 0.7679
    },
    {
      "x": 0.8435,
      "y": 0.7695
    },
    {
      "x": 0.8435,
      "y": 0.7711
    },
    {
      "x": 0.8464,
      "y": 0.7727
    },
    {
      "x": 0.8464,
      "y": 0.7744
    },
    {
      "x": 0.8464,
      "y": 0.776
    },
    {
      "x": 0.8464,
      "y": 0.7776
    },
    {
      "x": 0.8493,
      "y": 0.7792
    },
    {
      "x": 0.8493,
      "y": 0.7808
    },
    {
      "x": 0.8493,
      "y": 0.7825
    },
    {
      "x": 0.8493,
      "y": 0.7841
    },
    {
      "x": 0.8522,
      "y": 0.7857
    },
    {
      "x": 0.8522,
      "y": 0.7873
    },
    {
      "x": 0.8522,
      "y": 0.789
    },
    {
      "x": 0.8551,
      "y": 0.7906
    },
    {
      "x": 0.8551,
      "y": 0.7922
    },
    {
      "x": 0.8551,
      "y": 0.7938
    },
    {
      "x": 0.8551,
      "y": 0.7955
    },
    {
      "x": 0.858,
      "y": 0.7971
    },
    {
      "x": 0.858,
      "y": 0.7987
    },
    {
      "x": 0.858,
      "y": 0.8003
    },
    {
      "x": 0.858,
      "y": 0.8019
    },
    {
      "x": 0.8609,
      "y": 0.8036
    },
    {
      "x": 0.8609,
      "y": 0.8052
    },
    {
      "x": 0.8609,
      "y": 0.8068
    },
    {
      "x": 0.8609,
      "y": 0.8084
    },
    {
      "x": 0.8638,
      "y": 0.8101
    },
    {
      "x": 0.8638,
      "y": 0.8117
    },
    {
      "x": 0.8638,
      "y": 0.8133
    },
    {
      "x": 0.8667,
      "y": 0.8149
    },
    {
      "x": 0.8667,
      "y": 0.8166
    },
    {
      "x": 0.8667,
      "y": 0.8182
    },
    {
      "x": 0.8667,
      "y": 0.8198
    },
    {
      "x": 0.8696,
      "y": 0.8214
    },
    {
      "x": 0.8696,
      "y": 0.8231
    },
    {
      "x": 0.8696,
      "y": 0.8247
    },
    {
      "x": 0.8696,
      "y": 0.8263
    },
    {
      "x": 0.8725,
      "y": 0.8279
    },
    {
      "x": 0.8725,
      "y": 0.8295
    },
    {
      "x": 0.8725,
      "y": 0.8312
    },
    {
      "x": 0.8725,
      "y": 0.8328
    },
    {
      "x": 0.8754,
      "y": 0.8344
    },
    {
      "x": 0.8754,
      "y": 0.836
    },
    {
      "x": 0.8754,
      "y": 0.8377
    },
    {
      "x": 0.8783,
      "y": 0.8393
    },
    {
      "x": 0.8783,
      "y": 0.8409
    },
    {
      "x": 0.8783,
      "y": 0.8425
    },
    {
      "x": 0.8783,
      "y": 0.8442
    },
    {
      "x": 0.8812,
      "y": 0.8458
    },
    {
      "x": 0.8812,
      "y": 0.8474
    },
    {
      "x": 0.8812,
      "y": 0.849
    },
    {
      "x": 0.8812,
      "y": 0.8506
    },
    {
      "x": 0.8841,
      "y": 0.8523
    },
    {
      "x": 0.8841,
      "y": 0.8539
    },
    {
      "x": 0.8841,
      "y": 0.8555
    },
    {
      "x": 0.8841,
      "y": 0.8571
    },
    {
      "x": 0.887,
      "y": 0.8588
    },
    {
      "x": 0.887,
      "y": 0.8604
    },
    {
      "x": 0.887,
      "y": 0.862
    },
    {
      "x": 0.8899,
      "y": 0.8636
    },
    {
      "x": 0.8899,
      "y": 0.8653
    },
    {
      "x": 0.8899,
      "y": 0.8669
    },
    {
      "x": 0.8899,
      "y": 0.8685
    },
    {
      "x": 0.8928,
      "y": 0.8701
    },
    {
      "x": 0.8928,
      "y": 0.8718
    },
    {
      "x": 0.8928,
      "y": 0.8734
    },
    {
      "x": 0.8928,
      "y": 0.875
    },
    {
      "x": 0.8957,
      "y": 0.8766
    },
    {
      "x": 0.8957,
      "y": 0.8782
    },
    {
      "x": 0.8957,
      "y": 0.8799
    },
    {
      "x": 0.8957,
      "y": 0.8815
    },
    {
      "x": 0.8986,
      "y": 0.8831
    },
    {
      "x": 0.8986,
      "y": 0.8847
    },
    {
      "x": 0.8986,
      "y": 0.8864
    },
    {
      "x": 0.8986,
      "y": 0.888
    },
    {
      "x": 0.9014,
      "y": 0.8896
    },
    {
      "x": 0.9014,
      "y": 0.8912
    },
    {
      "x": 0.9014,
      "y": 0.8929
    },
    {
      "x": 0.9043,
      "y": 0.8945
    },
    {
      "x": 0.9043,
      "y": 0.8961
    },
    {
      "x": 0.9043,
      "y": 0.8977
    },
    {
      "x": 0.9043,
      "y": 0.8994
    },
    {
      "x": 0.9072,
      "y": 0.901
    },
    {
      "x": 0.9072,
      "y": 0.9026
    },
    {
      "x": 0.9072,
      "y": 0.9042
    },
    {
      "x": 0.9072,
      "y": 0.9058
    },
    {
      "x": 0.9101,
      "y": 0.9075
    },
    {
      "x": 0.9101,
      "y": 0.9091
    },
    {
      "x": 0.9101,
      "y": 0.9107
    },
    {
      "x": 0.9101,
      "y": 0.9123
    },
    {
      "x": 0.913,
      "y": 0.914
    },
    {
      "x": 0.913,
      "y": 0.9156
    },
    {
      "x": 0.913,
      "y": 0.9172
    },
    {
      "x": 0.913,
      "y": 0.9188
    },
    {
      "x": 0.9159,
      "y": 0.9205
    },
    {
      "x": 0.9159,
      "y": 0.9221
    },
    {
      "x": 0.9159,
      "y": 0.9237
    },
    {
      "x": 0.9188,
      "y": 0.9253
    },
    {
      "x": 0.9188,
      "y": 0.9269
    },
    {
      "x": 0.9188,
      "y": 0.9286
    },
    {
      "x": 0.9188,
      "y": 0.9302
    },
    {
      "x": 0.9217,
      "y": 0.9318
    },
    {
      "x": 0.9217,
      "y": 0.9334
    },
    {
      "x": 0.9217,
      "y": 0.9351
    },
    {
      "x": 0.9217,
      "y": 0.9367
    },
    {
      "x": 0.9246,
      "y": 0.9383
    },
    {
      "x": 0.9246,
      "y": 0.9399
    },
    {
      "x": 0.9246,
      "y": 0.9416
    },
    {
      "x": 0.9275,
      "y": 0.9432
    },
    {
      "x": 0.9275,
      "y": 0.9448
    },
    {
      "x": 0.9275,
      "y": 0.9464
    },
    {
      "x": 0.9275,
      "y": 0.9481
    },
    {
      "x": 0.9304,
      "y": 0.9497
    },
    {
      "x": 0.9304,
      "y": 0.9513
    },
    {
      "x": 0.9304,
      "y": 0.9529
    },
    {
      "x": 0.9333,
      "y": 0.9545
    },
    {
      "x": 0.9333,
      "y": 0.9562
    },
    {
      "x": 0.9333,
      "y": 0.9578
    },
    {
      "x": 0.9362,
      "y": 0.9594
    },
    {
      "x": 0.9362,
      "y": 0.961
    },
    {
      "x": 0.9333,
      "y": 0.9627
    },
    {
      "x": 0.0609,
      "y": 0.9659
    },
    {
      "x": 0.0638,
      "y": 0.9692
    }
  ]
}