{
  "letter": "D",
  "checkpointRadius": 0.05,
  "strokes": [
    {
      "id": 1,
      "checkpoints": [
        {
          "x": 0.1656,
          "y": 0.0649
        },
        {
          "x": 0.1534,
          "y": 0.0852
        },
        {
          "x": 0.1472,
          "y": 0.1095
        },
        {
          "x": 0.1442,
          "y": 0.1318
        },
        {
          "x": 0.1411,
          "y": 0.1562
        },
        {
          "x": 0.138,
          "y": 0.1785
        },
        {
          "x": 0.135,
          "y": 0.2028
        },
        {
          "x": 0.135,
          "y": 0.2272
        },
        {
          "x": 0.1319,
          "y": 0.2495
        },
        {
          "x": 0.1288,
          "y": 0.2738
        },
        {
          "x": 0.1258,
          "y": 0.2982
        },
        {
          "x": 0.1258,
          "y": 0.3225
        },
        {
          "x": 0.1227,
          "y": 0.3448
        },
        {
          "x": 0.1196,
          "y": 0.3692
        },
        {
          "x": 0.1166,
          "y": 0.3915
        },
        {
          "x": 0.1166,
          "y": 0.4158
        },
        {
          "x": 0.1135,
          "y": 0.4402
        },
        {
          "x": 0.1104,
          "y": 0.4645
        },
        {
          "x": 0.1074,
          "y": 0.4868
        },
        {
          "x": 0.1043,
          "y": 0.5112
        },
        {
          "x": 0.1043,
          "y": 0.5355
        },
        {
          "x": 0.1012,
          "y": 0.5578
        },
        {
          "x": 0.0982,
          "y": 0.5822
        },
        {
          "x": 0.0951,
          "y": 0.6045
        },
        {
          "x": 0.0951,
          "y": 0.6288
        },
        {
          "x": 0.092,
          "y": 0.6531
        },
        {
          "x": 0.089,
          "y": 0.6775
        },
        {
          "x": 0.0859,
          "y": 0.6998
        },
        {
          "x": 0.0859,
          "y": 0.7241
        },
        {
          "x": 0.0828,
          "y": 0.7485
        },
        {
          "x": 0.0798,
          "y": 0.7708
        },
        {
          "x": 0.0767,
          "y": 0.7951
        },
        {
          "x": 0.0736,
          "y": 0.8195
        },
        {
          "x": 0.0736,
          "y": 0.8438
        },
        {
          "x": 0.0706,
          "y": 0.8661
        },
        {
          "x": 0.0675,
          "y": 0.8905
        },
        {
          "x": 0.0675,
          "y": 0.9148
        },
        {
          "x": 0.0767,
          "y": 0.9371
        },
        {
          "x": 0.0828,
          "y": 0.9452
        }
      ],
      "comment": "worksheet"
    },
    {
      "id": 2,
      "checkpoints": [
        {
          "x": 0.7883,
          "y": 0.1379
        },
        {
          "x": 0.8129,
          "y": 0.1562
        },
        {
          "x": 0.8313,
          "y": 0.1744
        },
        {
          "x": 0.8497,
          "y": 0.1947
        },
        {
          "x": 0.865,
          "y": 0.213
        },
        {
          "x": 0.8804,
          "y": 0.2353
        },
        {
          "x": 0.8926,
          "y": 0.2556
        },
        {
          "x": 0.9018,
          "y": 0.2779
        },
        {
          "x": 0.911,
          "y": 0.2982
        },
        {
          "x": 0.9172,
          "y": 0.3225
        },
        {
          "x": 0.9233,
          "y": 0.3448
        },
        {
          "x": 0.9264,
          "y": 0.3671
        },
        {
          "x": 0.9294,
          "y": 0.3915
        },
        {
          "x": 0.9294,
          "y": 0.4158
        },
        {
          "x": 0.9294,
          "y": 0.4402
        },
        {
          "x": 0.9264,
          "y": 0.4645
        },
        {
          "x": 0.9264,
          "y": 0.4888
        },
        {
          "x": 0.9202,
          "y": 0.5112
        },
        {
          "x": 0.9172,
          "y": 0.5335
        },
        {
          "x": 0.911,
          "y": 0.5558
        },
        {
          "x": 0.9049,
          "y": 0.5781
        },
        {
          "x": 0.8957,
          "y": 0.6004
        },
        {
          "x": 0.8865,
          "y": 0.6227
        },
        {
          "x": 0.8742,
          "y": 0.643
        },
        {
          "x": 0.862,
          "y": 0.6653
        },
        {
          "x": 0.8497,
          "y": 0.6856
        },
        {
          "x": 0.8344,
          "y": 0.7059
        },
        {
          "x": 0.819,
          "y": 0.7262
        },
        {
          "x": 0.8006,
          "y": 0.7465
        },
        {
          "x": 0.7822,
          "y": 0.7647
        },
        {
          "x": 0.7638,
          "y": 0.783
        },
        {
          "x": 0.7423,
          "y": 0.8012
        },
        {
          "x": 0.7239,
          "y": 0.8154
        }
      ],
      "comment": "worksheet"
    }
  ]
}