{
  "letter": "O",
  "checkpointRadius": 0.08,
  "comment": "Bbox x=[0.341..0.652] y=[0.243..0.756]. 1 stroke: start upper-left, clockwise (down-left, bottom, right, up, closing near start).",
  "strokes": [
    {
      "id": 1,
      "comment": "Oval: start upper-left, go clockwise all the way around",
      "checkpoints": [
        {"x": 0.380, "y": 0.295},
        {"x": 0.341, "y": 0.371},
        {"x": 0.341, "y": 0.499},
        {"x": 0.380, "y": 0.628},
        {"x": 0.452, "y": 0.718},
        {"x": 0.541, "y": 0.718},
        {"x": 0.613, "y": 0.628},
        {"x": 0.652, "y": 0.499},
        {"x": 0.613, "y": 0.371},
        {"x": 0.541, "y": 0.281},
        {"x": 0.452, "y": 0.253}
      ]
    }
  ]
}
