{
  "letter": "Y",
  "checkpointRadius": 0.06,
  "strokes": [
    {
      "id": 1,
      "comment": "Left arm: top-left down to junction",
      "checkpoints": [
        {
          "x": 0.284,
          "y": 0.143
        },
        {
          "x": 0.35,
          "y": 0.29
        },
        {
          "x": 0.417,
          "y": 0.436
        },
        {
          "x": 0.515,
          "y": 0.507
        }
      ]
    },
    {
      "id": 2,
      "comment": "Right arm: top-right down to junction",
      "checkpoints": [
        {
          "x": 0.738,
          "y": 0.145
        },
        {
          "x": 0.626,
          "y": 0.325
        },
        {
          "x": 0.515,
          "y": 0.507
        }
      ]
    },
    {
      "id": 3,
      "comment": "Stem: junction down",
      "checkpoints": [
        {
          "x": 0.515,
          "y": 0.507
        },
        {
          "x": 0.472,
          "y": 0.667
        },
        {
          "x": 0.462,
          "y": 0.841
        }
      ]
    }
  ]
}
